yamltools4jedi/backend_hifiyaml/__init__.py
yamltools4jedi/backend_hifiyaml/core.py
yamltools4jedi/backend_pyyaml/__init__.py
yamltools4jedi/backend_pyyaml/core.py
yamltools4jedi-0.1.3.dist-info/licenses/LICENSE
yamltools4jedi-0.1.3.dist-info/METADATA
yamltools4jedi-0.1.3.dist-info/WHEEL
yamltools4jedi-0.1.3.dist-info/top_level.txt
yamltools4jedi-0.1.3.dist-info/RECORD
