Metadata-Version: 2.4
Name: yamltools4jedi
Version: 0.1.3
Summary: YAML tools to facilitate reading and editing JEDI super YAML files
Author-email: Guoqing Ge <Guoqing.Ge@noaa.gov>
Project-URL: Homepage, https://github.com/hifiyaml/yamltools4jedi/wiki
Project-URL: Source, https://github.com/hifiyaml/yamltools4jedi
Project-URL: Tracker, https://github.com/hifiyaml/yamltools4jedi/issues
Requires-Python: >=3.9
License-File: LICENSE
Requires-Dist: pyyaml>=6.0
Requires-Dist: hifiyaml>=0.1.6
Dynamic: license-file
